pygcgen/__init__.py
pygcgen/fetcher.py
pygcgen/generator.py
pygcgen/gui.py
pygcgen/main.py
pygcgen/options_parser.py
pygcgen/optionsfile_parser.py
pygcgen/pygcgen_exceptions.py
pygcgen/reader.py
pygcgen/version.py
pygcgen-0.2.4.dist-info/LICENSE.txt
pygcgen-0.2.4.dist-info/METADATA
pygcgen-0.2.4.dist-info/RECORD
pygcgen-0.2.4.dist-info/WHEEL
pygcgen-0.2.4.dist-info/entry_points.txt
pygcgen-0.2.4.dist-info/top_level.txt
