Metadata-Version: 2.1
Name: pygcgen
Version: 0.2.4
Summary: Generate changelog based on tags, issues and merged pull requests on GitHub.
Home-page: https://github.com/topic2k/pygcgen
Author: topic2k
Author-email: topic2k+pypi@gmail.com
Maintainer: topic2k
Maintainer-email: topic2k+pypi@gmail.com
License: MIT
Keywords: Automatic changelog generation
Platform: UNKNOWN
Classifier: Development Status :: 4 - Beta
Classifier: Environment :: Console
Classifier: Intended Audience :: Developers
Classifier: License :: OSI Approved :: MIT License
Classifier: Programming Language :: Python
Classifier: Programming Language :: Python :: 2.7
Classifier: Programming Language :: Python :: 3.6
Classifier: Topic :: Software Development :: Documentation
Requires-Dist: agithub
Requires-Dist: python-dateutil
